plato/__init__.py
plato/cmap.py
plato/geometry.py
plato/imp.py
plato/math.py
plato/mesh.py
plato/version.py
plato/draw/Arrows2D.py
plato/draw/Box.py
plato/draw/ConvexPolyhedra.py
plato/draw/ConvexSpheropolyhedra.py
plato/draw/DiskUnions.py
plato/draw/Disks.py
plato/draw/Ellipsoids.py
plato/draw/Lines.py
plato/draw/Mesh.py
plato/draw/Polygons.py
plato/draw/Scene.py
plato/draw/SpherePoints.py
plato/draw/SphereUnions.py
plato/draw/Spheres.py
plato/draw/Spheropolygons.py
plato/draw/Voronoi.py
plato/draw/__init__.py
plato/draw/internal.py
plato/draw/blender/ConvexPolyhedra.py
plato/draw/blender/Scene.py
plato/draw/blender/Spheres.py
plato/draw/blender/__init__.py
plato/draw/fresnel/Arrows2D.py
plato/draw/fresnel/Box.py
plato/draw/fresnel/ConvexPolyhedra.py
plato/draw/fresnel/Disks.py
plato/draw/fresnel/Ellipsoids.py
plato/draw/fresnel/FresnelPrimitive.py
plato/draw/fresnel/Lines.py
plato/draw/fresnel/Mesh.py
plato/draw/fresnel/Polygons.py
plato/draw/fresnel/Scene.py
plato/draw/fresnel/SphereUnions.py
plato/draw/fresnel/Spheres.py
plato/draw/fresnel/Spheropolygons.py
plato/draw/fresnel/__init__.py
plato/draw/matplotlib/Arrows2D.py
plato/draw/matplotlib/Box.py
plato/draw/matplotlib/ConvexPolyhedra.py
plato/draw/matplotlib/DiskUnions.py
plato/draw/matplotlib/Disks.py
plato/draw/matplotlib/Lines.py
plato/draw/matplotlib/Polygons.py
plato/draw/matplotlib/Scene.py
plato/draw/matplotlib/SpherePoints.py
plato/draw/matplotlib/Spheres.py
plato/draw/matplotlib/Spheropolygons.py
plato/draw/matplotlib/__init__.py
plato/draw/matplotlib/internal.py
plato/draw/povray/Box.py
plato/draw/povray/ConvexPolyhedra.py
plato/draw/povray/ConvexSpheropolyhedra.py
plato/draw/povray/Ellipsoids.py
plato/draw/povray/Lines.py
plato/draw/povray/Mesh.py
plato/draw/povray/Scene.py
plato/draw/povray/SphereUnions.py
plato/draw/povray/Spheres.py
plato/draw/povray/__init__.py
plato/draw/pythreejs/Box.py
plato/draw/pythreejs/ConvexPolyhedra.py
plato/draw/pythreejs/ConvexSpheropolyhedra.py
plato_draw-1.12.0.dist-info/LICENSE.txt
plato_draw-1.12.0.dist-info/METADATA
plato_draw-1.12.0.dist-info/WHEEL
plato_draw-1.12.0.dist-info/top_level.txt
plato_draw-1.12.0.dist-info/RECORD
