Metadata-Version: 2.1
Name: plato-draw
Version: 1.12.0
Summary: Geometry and visualization tools for collections of particles
Home-page: UNKNOWN
Author: Matthew Spellings
Author-email: mspells@umich.edu
License: BSD-3-Clause
Project-URL: Documentation, http://plato-draw.readthedocs.io/
Project-URL: Source, https://github.com/glotzerlab/plato
Platform: UNKNOWN
Classifier: Development Status :: 3 - Alpha
Classifier: License :: OSI Approved :: BSD License
Classifier: Programming Language :: Python :: 3
Classifier: Topic :: Multimedia :: Graphics
Classifier: Topic :: Scientific/Engineering :: Visualization
Requires-Python: >=3
Requires-Dist: numpy
Requires-Dist: scipy
Requires-Dist: rowan
Provides-Extra: pyside
Requires-Dist: pyside ; extra == 'pyside'
Requires-Dist: vispy (>=0.5.3) ; extra == 'pyside'
Provides-Extra: pyside2
Requires-Dist: pyside2 ; extra == 'pyside2'
Requires-Dist: vispy (>=0.6) ; extra == 'pyside2'
Provides-Extra: pythreejs
Requires-Dist: pythreejs ; extra == 'pythreejs'
